assart/__init__.py
assart/__main__.py
assart-0.2.0.dist-info/LICENSE
assart-0.2.0.dist-info/METADATA
assart-0.2.0.dist-info/WHEEL
assart-0.2.0.dist-info/entry_points.txt
assart-0.2.0.dist-info/top_level.txt
assart-0.2.0.dist-info/RECORD
