Metadata-Version: 2.1
Name: assart
Version: 0.2.0
Summary: A simple s3 analytics reporting tool
Home-page: https://github.com/mmcclellan/assart
Author: Michael McClellan
Author-email: mcclellan.m@gmail.com
License: MIT
Platform: UNKNOWN
Classifier: Programming Language :: Python :: 3
Classifier: License :: OSI Approved :: MIT License
Classifier: Operating System :: OS Independent
Requires-Python: >=3.6
Requires-Dist: boto3
